bayes_optim/__init__.py
bayes_optim/_base.py
bayes_optim/base.py
bayes_optim/bayes_opt.py
bayes_optim/extension.py
bayes_optim/mobo.py
bayes_optim/solution.py
bayes_optim/acquisition/__init__.py
bayes_optim/acquisition/acquisition_fun.py
bayes_optim/acquisition/optim/__init__.py
bayes_optim/acquisition/optim/mies.py
bayes_optim/acquisition/optim/one_plus_one_cma_es.py
bayes_optim/acquisition/optim/option.py
bayes_optim/multi_objective/__init__.py
bayes_optim/multi_objective/analytic.py
bayes_optim/search_space/__init__.py
bayes_optim/search_space/node.py
bayes_optim/search_space/samplers.py
bayes_optim/search_space/search_space.py
bayes_optim/search_space/variable.py
bayes_optim/surrogate/__init__.py
bayes_optim/surrogate/random_forest.py
bayes_optim/surrogate/gaussian_process/__init__.py
bayes_optim/surrogate/gaussian_process/boundary_handling.py
bayes_optim/surrogate/gaussian_process/cma_es.py
bayes_optim/surrogate/gaussian_process/gpr.py
bayes_optim/surrogate/gaussian_process/kernel.py
bayes_optim/surrogate/gaussian_process/trend.py
bayes_optim/surrogate/gaussian_process/utils.py
bayes_optim/utils/__init__.py
bayes_optim/utils/_daemon.py
bayes_optim/utils/exception.py
bayes_optim/utils/logger.py
bayes_optim/utils/utils.py
bayes_optim/utils/multi_objective/__init__.py
bayes_optim/utils/multi_objective/hypervolume.py
bayes_optim/utils/multi_objective/pareto.py
bayes_optim/utils/multi_objective/box_decompositions/__init__.py
bayes_optim/utils/multi_objective/box_decompositions/box_decomposition.py
bayes_optim/utils/multi_objective/box_decompositions/non_dominated.py
bayes_optim/utils/multi_objective/box_decompositions/utils.py
bayes_optim-0.3.0.dist-info/LICENSE
bayes_optim-0.3.0.dist-info/METADATA
bayes_optim-0.3.0.dist-info/WHEEL
bayes_optim-0.3.0.dist-info/top_level.txt
bayes_optim-0.3.0.dist-info/RECORD
