Metadata-Version: 2.1
Name: bayes-optim
Version: 0.3.0
Summary: A Bayesian Optimization Library
Home-page: https://github.com/wangronin/Bayesian-Optimization
Download-URL: https://github.com/wangronin/Bayesian-Optimization/archive/v0.1.3.tar.gz
Author: Hao Wang
Author-email: wangronin@gmail.com
Classifier: Programming Language :: Python :: 3
Classifier: License :: OSI Approved :: GNU General Public License v3 (GPLv3)
Requires-Python: >=3.7
License-File: LICENSE
Requires-Dist: dill (>=0.3.3)
Requires-Dist: joblib (>=1.0.0)
Requires-Dist: numpy (>=1.24.0)
Requires-Dist: pyDOE (>=0.3.8)
Requires-Dist: scikit-learn (>=1.2.2)
Requires-Dist: scipy (>=1.5.4)
Requires-Dist: sklearn (==0.0)
Requires-Dist: tabulate (>=0.8.7)
Requires-Dist: threadpoolctl (>=2.1.0)
Requires-Dist: requests (>=2.25.0)
Requires-Dist: requests-oauthlib (>=1.3.0)
Requires-Dist: sobol-seq (>=0.2.0)
Requires-Dist: py-expression-eval (>=0.3.13)
Requires-Dist: torch (>=2.0.1)
Requires-Dist: pytest (>=7.3.2)
